loggingpy/__init__.py
loggingpy/exceptions.py
loggingpy/log.py
loggingpy/sender.py
loggingpy/sink.py
logging_py-0.3.17.dist-info/LICENSE
logging_py-0.3.17.dist-info/METADATA
logging_py-0.3.17.dist-info/WHEEL
logging_py-0.3.17.dist-info/top_level.txt
logging_py-0.3.17.dist-info/RECORD
